{
  "alignments": [],
  "alternate_rendering_ids": [],
  "audit_ids": [],
  "audit_records": [],
  "canonical_rendering_ids": [],
  "concept_ids": [
    "cpt.ps078.v043.a.0001"
  ],
  "current_layer_state": {
    "latest_layer": "source",
    "locked_layers": []
  },
  "issue_links": [],
  "pr_links": [],
  "psalm_id": "ps078",
  "ref": "Psalm 78:43",
  "renderings": [],
  "review_decisions": [],
  "segmentation_type": "verse",
  "source_hebrew": "אֲשֶׁר־שָׂ֣ם בְּ֭מִצְרַיִם אֹֽתוֹתָ֑יו וּ֝מוֹפְתָ֗יו בִּשְׂדֵה־צֹֽעַן׃",
  "source_transliteration": "ʾăšer- śām bəmiṣrayim û biśəḏēh- ṣōʿan:",
  "status": "draft",
  "token_ids": [
    "ps078.v043.t001",
    "ps078.v043.t002",
    "ps078.v043.t003",
    "ps078.v043.t004",
    "ps078.v043.t005",
    "ps078.v043.t006",
    "ps078.v043.t007"
  ],
  "tokens": [
    {
      "compiler_features": {
        "component_count": 1,
        "conjunction_role": null,
        "construct_state": false,
        "discourse_marker": null,
        "divine_name": false,
        "english_parts": [
          "when"
        ],
        "gloss_fragments": [
          "when"
        ],
        "preposition_role": null,
        "raw_classes": [
          "rel"
        ],
        "raw_pos": [
          "particle"
        ],
        "suffix_pronoun": null,
        "temporal_pair_candidate": false
      },
      "corpus_occurrence_refs": [
        "Psalm 1:1",
        "Psalm 1:3",
        "Psalm 1:4",
        "Psalm 3:7",
        "Psalm 7:1",
        "Psalm 8:2",
        "Psalm 8:4",
        "Psalm 10:6",
        "Psalm 12:5",
        "Psalm 16:3",
        "Psalm 16:7",
        "Psalm 18:1",
        "Psalm 24:4",
        "Psalm 26:10",
        "Psalm 31:8",
        "Psalm 31:20",
        "Psalm 33:12",
        "Psalm 33:22",
        "Psalm 35:8",
        "Psalm 35:11",
        "Psalm 38:15",
        "Psalm 40:5",
        "Psalm 41:9",
        "Psalm 41:10"
      ],
      "display_gloss": "when",
      "enrichment_sources": {
        "macula": {
          "available_fields": [
            "word_sense"
          ],
          "missing_fields": [
            "syntax_role",
            "semantic_role",
            "referent"
          ],
          "status": "partial"
        },
        "oshb": {
          "available_fields": [
            "lemma",
            "strong",
            "morph_code",
            "morph_readable",
            "part_of_speech"
          ],
          "missing_fields": [
            "stem"
          ],
          "status": "partial"
        }
      },
      "gloss_parts": [
        "when"
      ],
      "lemma": "אֲשֶׁר",
      "missing_enrichments": [
        "oshb:stem",
        "macula:syntax_role",
        "macula:semantic_role",
        "macula:referent"
      ],
      "morph_code": "Tr",
      "morph_readable": "Tr",
      "normalized": "אשר",
      "occurrence_index": 48,
      "part_of_speech": "particle",
      "psalms_occurrence_refs": [
        "Psalm 1:1",
        "Psalm 1:3",
        "Psalm 1:4",
        "Psalm 3:7",
        "Psalm 7:1",
        "Psalm 8:2",
        "Psalm 8:4",
        "Psalm 10:6",
        "Psalm 12:5",
        "Psalm 16:3",
        "Psalm 16:7",
        "Psalm 18:1",
        "Psalm 24:4",
        "Psalm 26:10",
        "Psalm 31:8",
        "Psalm 31:20",
        "Psalm 33:12",
        "Psalm 33:22",
        "Psalm 35:8",
        "Psalm 35:11",
        "Psalm 38:15",
        "Psalm 40:5",
        "Psalm 41:9",
        "Psalm 41:10"
      ],
      "ref": "Psalm 78:43#1",
      "referent": null,
      "same_psalm_occurrence_refs": [
        "Psalm 78:3",
        "Psalm 78:4",
        "Psalm 78:5",
        "Psalm 78:11",
        "Psalm 78:42",
        "Psalm 78:68"
      ],
      "semantic_role": null,
      "stem": null,
      "strong": "H834",
      "surface": "אֲשֶׁר",
      "syntax_role": null,
      "token_id": "ps078.v043.t001",
      "transliteration": "ʾăšer-",
      "word_sense": "when"
    },
    {
      "compiler_features": {
        "component_count": 1,
        "conjunction_role": null,
        "construct_state": false,
        "discourse_marker": null,
        "divine_name": false,
        "english_parts": [
          "performed"
        ],
        "gloss_fragments": [
          "he performed"
        ],
        "preposition_role": null,
        "raw_classes": [
          "verb"
        ],
        "raw_pos": [
          "verb"
        ],
        "suffix_pronoun": null,
        "temporal_pair_candidate": false
      },
      "corpus_occurrence_refs": [
        "Psalm 19:5",
        "Psalm 40:5",
        "Psalm 46:9",
        "Psalm 50:23",
        "Psalm 52:9",
        "Psalm 54:5",
        "Psalm 66:2",
        "Psalm 66:9",
        "Psalm 66:11",
        "Psalm 74:4",
        "Psalm 79:1",
        "Psalm 85:14",
        "Psalm 89:26",
        "Psalm 89:30",
        "Psalm 89:41",
        "Psalm 91:9",
        "Psalm 104:3",
        "Psalm 104:9",
        "Psalm 105:27",
        "Psalm 107:33",
        "Psalm 107:35",
        "Psalm 107:41",
        "Psalm 109:5",
        "Psalm 147:14"
      ],
      "display_gloss": "he performed",
      "enrichment_sources": {
        "macula": {
          "available_fields": [
            "syntax_role",
            "word_sense"
          ],
          "missing_fields": [
            "semantic_role",
            "referent"
          ],
          "status": "partial"
        },
        "oshb": {
          "available_fields": [
            "lemma",
            "strong",
            "morph_code",
            "morph_readable",
            "part_of_speech",
            "stem"
          ],
          "missing_fields": [],
          "status": "complete"
        }
      },
      "gloss_parts": [
        "he.performed"
      ],
      "lemma": "שׂים",
      "missing_enrichments": [
        "macula:semantic_role",
        "macula:referent"
      ],
      "morph_code": "Vqp3ms",
      "morph_readable": "Vqp3ms",
      "normalized": "שם",
      "occurrence_index": 13,
      "part_of_speech": "verb",
      "psalms_occurrence_refs": [
        "Psalm 19:5",
        "Psalm 40:5",
        "Psalm 46:9",
        "Psalm 50:23",
        "Psalm 52:9",
        "Psalm 54:5",
        "Psalm 66:2",
        "Psalm 66:9",
        "Psalm 66:11",
        "Psalm 74:4",
        "Psalm 79:1",
        "Psalm 85:14",
        "Psalm 89:26",
        "Psalm 89:30",
        "Psalm 89:41",
        "Psalm 91:9",
        "Psalm 104:3",
        "Psalm 104:9",
        "Psalm 105:27",
        "Psalm 107:33",
        "Psalm 107:35",
        "Psalm 107:41",
        "Psalm 109:5",
        "Psalm 147:14"
      ],
      "ref": "Psalm 78:43#2",
      "referent": null,
      "same_psalm_occurrence_refs": [
        "Psalm 78:5",
        "Psalm 78:7"
      ],
      "semantic_role": null,
      "stem": "qal",
      "strong": "H7760",
      "surface": "שָׂ֣ם",
      "syntax_role": "v",
      "token_id": "ps078.v043.t002",
      "transliteration": "śām",
      "word_sense": "he.performed"
    },
    {
      "compiler_features": {
        "component_count": 2,
        "conjunction_role": null,
        "construct_state": false,
        "discourse_marker": null,
        "divine_name": false,
        "english_parts": [
          "in",
          "Egypt"
        ],
        "gloss_fragments": [
          "in",
          "Egypt"
        ],
        "preposition_role": "in",
        "raw_classes": [
          "prep",
          "noun"
        ],
        "raw_pos": [
          "preposition",
          "noun"
        ],
        "suffix_pronoun": null,
        "temporal_pair_candidate": false
      },
      "corpus_occurrence_refs": [
        "Psalm 68:32",
        "Psalm 80:9",
        "Psalm 81:6",
        "Psalm 81:11",
        "Psalm 105:23",
        "Psalm 105:38",
        "Psalm 106:7",
        "Psalm 106:21",
        "Psalm 114:1",
        "Psalm 135:8",
        "Psalm 135:9",
        "Psalm 136:10"
      ],
      "display_gloss": "in Egypt",
      "enrichment_sources": {
        "macula": {
          "available_fields": [
            "word_sense"
          ],
          "missing_fields": [
            "syntax_role",
            "semantic_role",
            "referent"
          ],
          "status": "partial"
        },
        "oshb": {
          "available_fields": [
            "lemma",
            "strong",
            "morph_code",
            "morph_readable",
            "part_of_speech"
          ],
          "missing_fields": [
            "stem"
          ],
          "status": "partial"
        }
      },
      "gloss_parts": [
        "in",
        "Egypt"
      ],
      "lemma": "מִצְרַיִם",
      "missing_enrichments": [
        "oshb:stem",
        "macula:syntax_role",
        "macula:semantic_role",
        "macula:referent"
      ],
      "morph_code": "R/Np",
      "morph_readable": "R/Np",
      "normalized": "במצרים",
      "occurrence_index": 3,
      "part_of_speech": "noun",
      "psalms_occurrence_refs": [
        "Psalm 68:32",
        "Psalm 80:9",
        "Psalm 81:6",
        "Psalm 81:11",
        "Psalm 105:23",
        "Psalm 105:38",
        "Psalm 106:7",
        "Psalm 106:21",
        "Psalm 114:1",
        "Psalm 135:8",
        "Psalm 135:9",
        "Psalm 136:10"
      ],
      "ref": "Psalm 78:43#3",
      "referent": null,
      "same_psalm_occurrence_refs": [
        "Psalm 78:12",
        "Psalm 78:51"
      ],
      "semantic_role": null,
      "stem": null,
      "strong": "H4714",
      "surface": "בְּ֭מִצְרַיִם",
      "syntax_role": null,
      "token_id": "ps078.v043.t003",
      "transliteration": "bəmiṣrayim",
      "word_sense": "Egypt"
    },
    {
      "compiler_features": {
        "component_count": 2,
        "conjunction_role": null,
        "construct_state": true,
        "discourse_marker": null,
        "divine_name": false,
        "english_parts": [
          "signs",
          "his"
        ],
        "gloss_fragments": [
          "signs",
          "his"
        ],
        "preposition_role": null,
        "raw_classes": [
          "noun",
          "pron"
        ],
        "raw_pos": [
          "noun",
          "suffix"
        ],
        "suffix_pronoun": {
          "gender": "masculine",
          "number": "singular",
          "person": "third",
          "text": "his"
        },
        "temporal_pair_candidate": false
      },
      "corpus_occurrence_refs": [
        "Psalm 1:2",
        "Psalm 1:3",
        "Psalm 1:4",
        "Psalm 2:2",
        "Psalm 2:3",
        "Psalm 2:4",
        "Psalm 2:5",
        "Psalm 2:6",
        "Psalm 2:7",
        "Psalm 2:8",
        "Psalm 2:9",
        "Psalm 2:12",
        "Psalm 3:1",
        "Psalm 3:2",
        "Psalm 3:3",
        "Psalm 3:4",
        "Psalm 3:5",
        "Psalm 3:6",
        "Psalm 3:7",
        "Psalm 3:8",
        "Psalm 3:9",
        "Psalm 4:2",
        "Psalm 4:3",
        "Psalm 4:4"
      ],
      "display_gloss": "his signs",
      "enrichment_sources": {
        "macula": {
          "available_fields": [
            "word_sense"
          ],
          "missing_fields": [
            "syntax_role",
            "semantic_role",
            "referent"
          ],
          "status": "partial"
        },
        "oshb": {
          "available_fields": [
            "lemma",
            "strong",
            "morph_code",
            "morph_readable",
            "part_of_speech"
          ],
          "missing_fields": [
            "stem"
          ],
          "status": "partial"
        }
      },
      "gloss_parts": [
        "signs",
        "his"
      ],
      "lemma": "הוּא",
      "missing_enrichments": [
        "oshb:stem",
        "macula:syntax_role",
        "macula:semantic_role",
        "macula:referent"
      ],
      "morph_code": "Ncbpc/Sp3ms",
      "morph_readable": "Ncbpc/Sp3ms",
      "normalized": "אתותיו",
      "occurrence_index": 2467,
      "part_of_speech": "suffix",
      "psalms_occurrence_refs": [
        "Psalm 1:2",
        "Psalm 1:3",
        "Psalm 1:4",
        "Psalm 2:2",
        "Psalm 2:3",
        "Psalm 2:4",
        "Psalm 2:5",
        "Psalm 2:6",
        "Psalm 2:7",
        "Psalm 2:8",
        "Psalm 2:9",
        "Psalm 2:12",
        "Psalm 3:1",
        "Psalm 3:2",
        "Psalm 3:3",
        "Psalm 3:4",
        "Psalm 3:5",
        "Psalm 3:6",
        "Psalm 3:7",
        "Psalm 3:8",
        "Psalm 3:9",
        "Psalm 4:2",
        "Psalm 4:3",
        "Psalm 4:4"
      ],
      "ref": "Psalm 78:43#4",
      "referent": null,
      "same_psalm_occurrence_refs": [
        "Psalm 78:1",
        "Psalm 78:2",
        "Psalm 78:3",
        "Psalm 78:4",
        "Psalm 78:5",
        "Psalm 78:6",
        "Psalm 78:7",
        "Psalm 78:8",
        "Psalm 78:10",
        "Psalm 78:11",
        "Psalm 78:12",
        "Psalm 78:13"
      ],
      "semantic_role": null,
      "stem": null,
      "strong": "H226",
      "surface": "אֹֽתוֹתָ֑יו",
      "syntax_role": null,
      "token_id": "ps078.v043.t004",
      "transliteration": null,
      "word_sense": "his"
    },
    {
      "compiler_features": {
        "component_count": 3,
        "conjunction_role": "additive",
        "construct_state": true,
        "discourse_marker": null,
        "divine_name": false,
        "english_parts": [
          "and",
          "wonders",
          "his"
        ],
        "gloss_fragments": [
          "and",
          "wonders",
          "his"
        ],
        "preposition_role": null,
        "raw_classes": [
          "cj",
          "noun",
          "pron"
        ],
        "raw_pos": [
          "conjunction",
          "noun",
          "suffix"
        ],
        "suffix_pronoun": {
          "gender": "masculine",
          "number": "singular",
          "person": "third",
          "text": "his"
        },
        "temporal_pair_candidate": false
      },
      "corpus_occurrence_refs": [
        "Psalm 1:2",
        "Psalm 1:3",
        "Psalm 1:4",
        "Psalm 2:2",
        "Psalm 2:3",
        "Psalm 2:4",
        "Psalm 2:5",
        "Psalm 2:6",
        "Psalm 2:7",
        "Psalm 2:8",
        "Psalm 2:9",
        "Psalm 2:12",
        "Psalm 3:1",
        "Psalm 3:2",
        "Psalm 3:3",
        "Psalm 3:4",
        "Psalm 3:5",
        "Psalm 3:6",
        "Psalm 3:7",
        "Psalm 3:8",
        "Psalm 3:9",
        "Psalm 4:2",
        "Psalm 4:3",
        "Psalm 4:4"
      ],
      "display_gloss": "and his wonders",
      "enrichment_sources": {
        "macula": {
          "available_fields": [
            "word_sense"
          ],
          "missing_fields": [
            "syntax_role",
            "semantic_role",
            "referent"
          ],
          "status": "partial"
        },
        "oshb": {
          "available_fields": [
            "lemma",
            "strong",
            "morph_code",
            "morph_readable",
            "part_of_speech"
          ],
          "missing_fields": [
            "stem"
          ],
          "status": "partial"
        }
      },
      "gloss_parts": [
        "and",
        "wonders",
        "his"
      ],
      "lemma": "הוּא",
      "missing_enrichments": [
        "oshb:stem",
        "macula:syntax_role",
        "macula:semantic_role",
        "macula:referent"
      ],
      "morph_code": "C/Ncmpc/Sp3ms",
      "morph_readable": "C/Ncmpc/Sp3ms",
      "normalized": "ומופתיו",
      "occurrence_index": 2468,
      "part_of_speech": "suffix",
      "psalms_occurrence_refs": [
        "Psalm 1:2",
        "Psalm 1:3",
        "Psalm 1:4",
        "Psalm 2:2",
        "Psalm 2:3",
        "Psalm 2:4",
        "Psalm 2:5",
        "Psalm 2:6",
        "Psalm 2:7",
        "Psalm 2:8",
        "Psalm 2:9",
        "Psalm 2:12",
        "Psalm 3:1",
        "Psalm 3:2",
        "Psalm 3:3",
        "Psalm 3:4",
        "Psalm 3:5",
        "Psalm 3:6",
        "Psalm 3:7",
        "Psalm 3:8",
        "Psalm 3:9",
        "Psalm 4:2",
        "Psalm 4:3",
        "Psalm 4:4"
      ],
      "ref": "Psalm 78:43#5",
      "referent": null,
      "same_psalm_occurrence_refs": [
        "Psalm 78:1",
        "Psalm 78:2",
        "Psalm 78:3",
        "Psalm 78:4",
        "Psalm 78:5",
        "Psalm 78:6",
        "Psalm 78:7",
        "Psalm 78:8",
        "Psalm 78:10",
        "Psalm 78:11",
        "Psalm 78:12",
        "Psalm 78:13"
      ],
      "semantic_role": null,
      "stem": null,
      "strong": "H4159",
      "surface": "וּ֝מוֹפְתָ֗יו",
      "syntax_role": null,
      "token_id": "ps078.v043.t005",
      "transliteration": "û",
      "word_sense": "his"
    },
    {
      "compiler_features": {
        "component_count": 2,
        "conjunction_role": null,
        "construct_state": true,
        "discourse_marker": null,
        "divine_name": false,
        "english_parts": [
          "in",
          "region"
        ],
        "gloss_fragments": [
          "in",
          "the region"
        ],
        "preposition_role": "in",
        "raw_classes": [
          "prep",
          "noun"
        ],
        "raw_pos": [
          "preposition",
          "noun"
        ],
        "suffix_pronoun": null,
        "temporal_pair_candidate": false
      },
      "corpus_occurrence_refs": [
        "Psalm 103:15",
        "Psalm 107:37",
        "Psalm 132:6"
      ],
      "display_gloss": "in the region",
      "enrichment_sources": {
        "macula": {
          "available_fields": [
            "word_sense"
          ],
          "missing_fields": [
            "syntax_role",
            "semantic_role",
            "referent"
          ],
          "status": "partial"
        },
        "oshb": {
          "available_fields": [
            "lemma",
            "strong",
            "morph_code",
            "morph_readable",
            "part_of_speech"
          ],
          "missing_fields": [
            "stem"
          ],
          "status": "partial"
        }
      },
      "gloss_parts": [
        "in",
        "the.region"
      ],
      "lemma": "שָׂדֶה",
      "missing_enrichments": [
        "oshb:stem",
        "macula:syntax_role",
        "macula:semantic_role",
        "macula:referent"
      ],
      "morph_code": "R/Ncmsc",
      "morph_readable": "R/Ncmsc",
      "normalized": "בשדה",
      "occurrence_index": 2,
      "part_of_speech": "noun",
      "psalms_occurrence_refs": [
        "Psalm 103:15",
        "Psalm 107:37",
        "Psalm 132:6"
      ],
      "ref": "Psalm 78:43#6",
      "referent": null,
      "same_psalm_occurrence_refs": [
        "Psalm 78:12"
      ],
      "semantic_role": null,
      "stem": null,
      "strong": "H7704",
      "surface": "בִּשְׂדֵה",
      "syntax_role": null,
      "token_id": "ps078.v043.t006",
      "transliteration": "biśəḏēh-",
      "word_sense": "the.region"
    },
    {
      "compiler_features": {
        "component_count": 1,
        "conjunction_role": null,
        "construct_state": false,
        "discourse_marker": null,
        "divine_name": false,
        "english_parts": [
          "Zoan"
        ],
        "gloss_fragments": [
          "of Zoan"
        ],
        "preposition_role": null,
        "raw_classes": [
          "noun"
        ],
        "raw_pos": [
          "noun"
        ],
        "suffix_pronoun": null,
        "temporal_pair_candidate": false
      },
      "corpus_occurrence_refs": [],
      "display_gloss": "of Zoan",
      "enrichment_sources": {
        "macula": {
          "available_fields": [
            "word_sense"
          ],
          "missing_fields": [
            "syntax_role",
            "semantic_role",
            "referent"
          ],
          "status": "partial"
        },
        "oshb": {
          "available_fields": [
            "lemma",
            "strong",
            "morph_code",
            "morph_readable",
            "part_of_speech"
          ],
          "missing_fields": [
            "stem"
          ],
          "status": "partial"
        }
      },
      "gloss_parts": [
        "of.Zoan"
      ],
      "lemma": "צֹעַן",
      "missing_enrichments": [
        "oshb:stem",
        "macula:syntax_role",
        "macula:semantic_role",
        "macula:referent"
      ],
      "morph_code": "Np",
      "morph_readable": "Np",
      "normalized": "צען",
      "occurrence_index": 2,
      "part_of_speech": "noun",
      "psalms_occurrence_refs": [],
      "ref": "Psalm 78:43#7",
      "referent": null,
      "same_psalm_occurrence_refs": [
        "Psalm 78:12"
      ],
      "semantic_role": null,
      "stem": null,
      "strong": "H6814",
      "surface": "צֹֽעַן",
      "syntax_role": null,
      "token_id": "ps078.v043.t007",
      "transliteration": "ṣōʿan:",
      "word_sense": "of.Zoan"
    }
  ],
  "unit_id": "ps078.v043.a",
  "witnesses": [
    {
      "language": "en",
      "ref": "Psalm 78:43",
      "source_id": "kjv",
      "source_url": "https://ebible.org/eng-kjv2006/PSA078.htm",
      "text": "How he had wrought his signs in Egypt, and his wonders in the field of Zoan:",
      "versionTitle": "King James Version"
    },
    {
      "language": "en",
      "ref": "Psalm 78:43",
      "source_id": "asv",
      "source_url": "https://ebible.org/eng-asv/PSA078.htm",
      "text": "How he set his signs in Egypt, And his wonders in the field of Zoan,",
      "versionTitle": "American Standard Version"
    },
    {
      "language": "en",
      "ref": "Psalm 78:43",
      "source_id": "web",
      "source_url": "https://ebible.org/engwebp/PSA078.htm",
      "text": "how he set his signs in Egypt, his wonders in the field of Zoan,",
      "versionTitle": "World English Bible"
    }
  ]
}
